{
  "coinId": "htx-dao",
  "generatedAt": "2026-07-15T15:00:07.443948Z",
  "modelVersion": "lstm-2.0.0",
  "series": [
    {
      "time": "2026-07-08T16:00:00Z",
      "actualIndex": 100.0,
      "predictedIndex": 100.0
    },
    {
      "time": "2026-07-08T17:00:00Z",
      "actualIndex": 100.5603,
      "predictedIndex": 99.9653
    },
    {
      "time": "2026-07-08T18:00:00Z",
      "actualIndex": 101.1383,
      "predictedIndex": 100.5246
    },
    {
      "time": "2026-07-08T19:00:00Z",
      "actualIndex": 101.4362,
      "predictedIndex": 101.1017
    },
    {
      "time": "2026-07-08T20:00:00Z",
      "actualIndex": 101.2878,
      "predictedIndex": 101.3991
    },
    {
      "time": "2026-07-08T21:00:00Z",
      "actualIndex": 101.4277,
      "predictedIndex": 101.2502
    },
    {
      "time": "2026-07-08T22:00:00Z",
      "actualIndex": 101.7026,
      "predictedIndex": 101.3899
    },
    {
      "time": "2026-07-08T23:00:00Z",
      "actualIndex": 101.3664,
      "predictedIndex": 101.6644
    },
    {
      "time": "2026-07-09T00:00:00Z",
      "actualIndex": 100.9642,
      "predictedIndex": 101.3274
    },
    {
      "time": "2026-07-09T01:00:00Z",
      "actualIndex": 99.8165,
      "predictedIndex": 100.9247
    },
    {
      "time": "2026-07-09T02:00:00Z",
      "actualIndex": 100.1958,
      "predictedIndex": 99.7773
    },
    {
      "time": "2026-07-09T03:00:00Z",
      "actualIndex": 100.0469,
      "predictedIndex": 100.1557
    },
    {
      "time": "2026-07-09T04:00:00Z",
      "actualIndex": 100.5967,
      "predictedIndex": 100.0059
    },
    {
      "time": "2026-07-09T05:00:00Z",
      "actualIndex": 100.4747,
      "predictedIndex": 100.5551
    },
    {
      "time": "2026-07-09T06:00:00Z",
      "actualIndex": 100.489,
      "predictedIndex": 100.4343
    },
    {
      "time": "2026-07-09T07:00:00Z",
      "actualIndex": 100.4955,
      "predictedIndex": 100.4508
    },
    {
      "time": "2026-07-09T08:00:00Z",
      "actualIndex": 101.1129,
      "predictedIndex": 100.4617
    },
    {
      "time": "2026-07-09T09:00:00Z",
      "actualIndex": 101.244,
      "predictedIndex": 101.0841
    },
    {
      "time": "2026-07-09T10:00:00Z",
      "actualIndex": 101.1041,
      "predictedIndex": 101.2223
    },
    {
      "time": "2026-07-09T11:00:00Z",
      "actualIndex": 102.341,
      "predictedIndex": 101.0901
    },
    {
      "time": "2026-07-09T12:00:00Z",
      "actualIndex": 102.1143,
      "predictedIndex": 102.3289
    },
    {
      "time": "2026-07-09T13:00:00Z",
      "actualIndex": 100.8965,
      "predictedIndex": 102.1031
    },
    {
      "time": "2026-07-09T14:00:00Z",
      "actualIndex": 100.8844,
      "predictedIndex": 100.8871
    },
    {
      "time": "2026-07-09T15:00:00Z",
      "actualIndex": 100.7251,
      "predictedIndex": 100.8762
    },
    {
      "time": "2026-07-09T16:00:00Z",
      "actualIndex": 100.828,
      "predictedIndex": 100.7193
    },
    {
      "time": "2026-07-09T17:00:00Z",
      "actualIndex": 100.8407,
      "predictedIndex": 100.8243
    },
    {
      "time": "2026-07-09T18:00:00Z",
      "actualIndex": 100.9557,
      "predictedIndex": 100.8378
    },
    {
      "time": "2026-07-09T19:00:00Z",
      "actualIndex": 100.7724,
      "predictedIndex": 100.9537
    },
    {
      "time": "2026-07-09T20:00:00Z",
      "actualIndex": 100.6999,
      "predictedIndex": 100.7702
    },
    {
      "time": "2026-07-09T21:00:00Z",
      "actualIndex": 100.9803,
      "predictedIndex": 100.6978
    },
    {
      "time": "2026-07-09T22:00:00Z",
      "actualIndex": 100.8525,
      "predictedIndex": 100.9782
    },
    {
      "time": "2026-07-09T23:00:00Z",
      "actualIndex": 100.7588,
      "predictedIndex": 100.8503
    },
    {
      "time": "2026-07-10T00:00:00Z",
      "actualIndex": 100.7992,
      "predictedIndex": 100.7567
    },
    {
      "time": "2026-07-10T01:00:00Z",
      "actualIndex": 101.1399,
      "predictedIndex": 100.7969
    },
    {
      "time": "2026-07-10T02:00:00Z",
      "actualIndex": 101.1843,
      "predictedIndex": 101.1377
    },
    {
      "time": "2026-07-10T03:00:00Z",
      "actualIndex": 101.2735,
      "predictedIndex": 101.1822
    },
    {
      "time": "2026-07-10T04:00:00Z",
      "actualIndex": 101.0002,
      "predictedIndex": 101.2713
    },
    {
      "time": "2026-07-10T05:00:00Z",
      "actualIndex": 101.1274,
      "predictedIndex": 100.9982
    },
    {
      "time": "2026-07-10T06:00:00Z",
      "actualIndex": 101.0126,
      "predictedIndex": 101.1254
    },
    {
      "time": "2026-07-10T07:00:00Z",
      "actualIndex": 100.7665,
      "predictedIndex": 101.0107
    },
    {
      "time": "2026-07-10T08:00:00Z",
      "actualIndex": 100.4577,
      "predictedIndex": 100.765
    },
    {
      "time": "2026-07-10T09:00:00Z",
      "actualIndex": 100.1061,
      "predictedIndex": 100.4565
    },
    {
      "time": "2026-07-10T10:00:00Z",
      "actualIndex": 100.3677,
      "predictedIndex": 100.1052
    },
    {
      "time": "2026-07-10T11:00:00Z",
      "actualIndex": 100.0888,
      "predictedIndex": 100.367
    },
    {
      "time": "2026-07-10T12:00:00Z",
      "actualIndex": 99.9044,
      "predictedIndex": 100.0882
    },
    {
      "time": "2026-07-10T13:00:00Z",
      "actualIndex": 99.4928,
      "predictedIndex": 99.9038
    },
    {
      "time": "2026-07-10T14:00:00Z",
      "actualIndex": 99.6642,
      "predictedIndex": 99.4924
    },
    {
      "time": "2026-07-10T15:00:00Z",
      "actualIndex": 99.9976,
      "predictedIndex": 99.6637
    },
    {
      "time": "2026-07-10T16:00:00Z",
      "actualIndex": 100.1054,
      "predictedIndex": 99.9974
    },
    {
      "time": "2026-07-10T17:00:00Z",
      "actualIndex": 100.1597,
      "predictedIndex": 100.1055
    },
    {
      "time": "2026-07-10T18:00:00Z",
      "actualIndex": 100.1595,
      "predictedIndex": 100.1604
    },
    {
      "time": "2026-07-10T19:00:00Z",
      "actualIndex": 100.3515,
      "predictedIndex": 100.1608
    },
    {
      "time": "2026-07-10T20:00:00Z",
      "actualIndex": 100.4016,
      "predictedIndex": 100.3535
    },
    {
      "time": "2026-07-10T21:00:00Z",
      "actualIndex": 100.4685,
      "predictedIndex": 100.4041
    },
    {
      "time": "2026-07-10T22:00:00Z",
      "actualIndex": 100.4754,
      "predictedIndex": 100.4715
    },
    {
      "time": "2026-07-10T23:00:00Z",
      "actualIndex": 100.421,
      "predictedIndex": 100.4791
    },
    {
      "time": "2026-07-11T00:00:00Z",
      "actualIndex": 100.1261,
      "predictedIndex": 100.4251
    },
    {
      "time": "2026-07-11T01:00:00Z",
      "actualIndex": 100.4564,
      "predictedIndex": 100.1302
    },
    {
      "time": "2026-07-11T02:00:00Z",
      "actualIndex": 100.6621,
      "predictedIndex": 100.4606
    },
    {
      "time": "2026-07-11T03:00:00Z",
      "actualIndex": 100.3629,
      "predictedIndex": 100.6663
    },
    {
      "time": "2026-07-11T04:00:00Z",
      "actualIndex": 100.3451,
      "predictedIndex": 100.367
    },
    {
      "time": "2026-07-11T05:00:00Z",
      "actualIndex": 100.4701,
      "predictedIndex": 100.3494
    },
    {
      "time": "2026-07-11T06:00:00Z",
      "actualIndex": 100.6205,
      "predictedIndex": 100.4744
    },
    {
      "time": "2026-07-11T07:00:00Z",
      "actualIndex": 100.4268,
      "predictedIndex": 100.6247
    },
    {
      "time": "2026-07-11T08:00:00Z",
      "actualIndex": 100.1758,
      "predictedIndex": 100.4312
    },
    {
      "time": "2026-07-11T09:00:00Z",
      "actualIndex": 100.3347,
      "predictedIndex": 100.1815
    },
    {
      "time": "2026-07-11T10:00:00Z",
      "actualIndex": 100.0959,
      "predictedIndex": 100.3411
    },
    {
      "time": "2026-07-11T11:00:00Z",
      "actualIndex": 100.001,
      "predictedIndex": 100.1029
    },
    {
      "time": "2026-07-11T12:00:00Z",
      "actualIndex": 99.9399,
      "predictedIndex": 100.0087
    },
    {
      "time": "2026-07-11T13:00:00Z",
      "actualIndex": 100.3115,
      "predictedIndex": 99.9478
    },
    {
      "time": "2026-07-11T14:00:00Z",
      "actualIndex": 100.2701,
      "predictedIndex": 100.3192
    },
    {
      "time": "2026-07-11T15:00:00Z",
      "actualIndex": 100.2758,
      "predictedIndex": 100.2784
    },
    {
      "time": "2026-07-11T16:00:00Z",
      "actualIndex": 100.1218,
      "predictedIndex": 100.2845
    },
    {
      "time": "2026-07-11T17:00:00Z",
      "actualIndex": 100.1247,
      "predictedIndex": 100.1307
    },
    {
      "time": "2026-07-11T18:00:00Z",
      "actualIndex": 100.4487,
      "predictedIndex": 100.1337
    },
    {
      "time": "2026-07-11T19:00:00Z",
      "actualIndex": 100.3984,
      "predictedIndex": 100.4582
    },
    {
      "time": "2026-07-11T20:00:00Z",
      "actualIndex": 100.293,
      "predictedIndex": 100.4078
    },
    {
      "time": "2026-07-11T21:00:00Z",
      "actualIndex": 100.3399,
      "predictedIndex": 100.3022
    },
    {
      "time": "2026-07-11T22:00:00Z",
      "actualIndex": 100.239,
      "predictedIndex": 100.3488
    },
    {
      "time": "2026-07-11T23:00:00Z",
      "actualIndex": 100.3931,
      "predictedIndex": 100.2474
    },
    {
      "time": "2026-07-12T00:00:00Z",
      "actualIndex": 100.2381,
      "predictedIndex": 100.4012
    },
    {
      "time": "2026-07-12T01:00:00Z",
      "actualIndex": 100.124,
      "predictedIndex": 100.2459
    },
    {
      "time": "2026-07-12T02:00:00Z",
      "actualIndex": 100.1323,
      "predictedIndex": 100.1314
    },
    {
      "time": "2026-07-12T03:00:00Z",
      "actualIndex": 100.1774,
      "predictedIndex": 100.1395
    },
    {
      "time": "2026-07-12T04:00:00Z",
      "actualIndex": 100.2425,
      "predictedIndex": 100.1844
    },
    {
      "time": "2026-07-12T05:00:00Z",
      "actualIndex": 100.2327,
      "predictedIndex": 100.2494
    },
    {
      "time": "2026-07-12T06:00:00Z",
      "actualIndex": 100.1814,
      "predictedIndex": 100.2397
    },
    {
      "time": "2026-07-12T07:00:00Z",
      "actualIndex": 100.3931,
      "predictedIndex": 100.1883
    },
    {
      "time": "2026-07-12T08:00:00Z",
      "actualIndex": 100.5086,
      "predictedIndex": 100.3999
    },
    {
      "time": "2026-07-12T09:00:00Z",
      "actualIndex": 100.4975,
      "predictedIndex": 100.5154
    },
    {
      "time": "2026-07-12T10:00:00Z",
      "actualIndex": 100.7775,
      "predictedIndex": 100.5043
    },
    {
      "time": "2026-07-12T11:00:00Z",
      "actualIndex": 100.7701,
      "predictedIndex": 100.7844
    },
    {
      "time": "2026-07-12T12:00:00Z",
      "actualIndex": 100.6205,
      "predictedIndex": 100.7768
    },
    {
      "time": "2026-07-12T13:00:00Z",
      "actualIndex": 100.7742,
      "predictedIndex": 100.6271
    },
    {
      "time": "2026-07-12T14:00:00Z",
      "actualIndex": 100.9552,
      "predictedIndex": 100.7804
    },
    {
      "time": "2026-07-12T15:00:00Z",
      "actualIndex": 100.7307,
      "predictedIndex": 100.9617
    },
    {
      "time": "2026-07-12T16:00:00Z",
      "actualIndex": 100.8398,
      "predictedIndex": 100.737
    },
    {
      "time": "2026-07-12T17:00:00Z",
      "actualIndex": 100.6334,
      "predictedIndex": 100.8462
    },
    {
      "time": "2026-07-12T18:00:00Z",
      "actualIndex": 100.5757,
      "predictedIndex": 100.6398
    },
    {
      "time": "2026-07-12T19:00:00Z",
      "actualIndex": 101.056,
      "predictedIndex": 100.582
    },
    {
      "time": "2026-07-12T20:00:00Z",
      "actualIndex": 101.0625,
      "predictedIndex": 101.0623
    },
    {
      "time": "2026-07-12T21:00:00Z",
      "actualIndex": 101.1532,
      "predictedIndex": 101.0686
    },
    {
      "time": "2026-07-12T22:00:00Z",
      "actualIndex": 101.0038,
      "predictedIndex": 101.1591
    },
    {
      "time": "2026-07-12T23:00:00Z",
      "actualIndex": 100.9296,
      "predictedIndex": 101.0096
    },
    {
      "time": "2026-07-13T00:00:00Z",
      "actualIndex": 100.8398,
      "predictedIndex": 100.9352
    },
    {
      "time": "2026-07-13T01:00:00Z",
      "actualIndex": 101.0584,
      "predictedIndex": 100.8451
    },
    {
      "time": "2026-07-13T02:00:00Z",
      "actualIndex": 101.0589,
      "predictedIndex": 101.0634
    },
    {
      "time": "2026-07-13T03:00:00Z",
      "actualIndex": 100.9008,
      "predictedIndex": 101.0637
    },
    {
      "time": "2026-07-13T04:00:00Z",
      "actualIndex": 100.5706,
      "predictedIndex": 100.9053
    },
    {
      "time": "2026-07-13T05:00:00Z",
      "actualIndex": 100.4547,
      "predictedIndex": 100.575
    },
    {
      "time": "2026-07-13T06:00:00Z",
      "actualIndex": 100.4572,
      "predictedIndex": 100.4589
    },
    {
      "time": "2026-07-13T07:00:00Z",
      "actualIndex": 99.7976,
      "predictedIndex": 100.4612
    },
    {
      "time": "2026-07-13T08:00:00Z",
      "actualIndex": 99.8962,
      "predictedIndex": 99.8015
    },
    {
      "time": "2026-07-13T09:00:00Z",
      "actualIndex": 100.0341,
      "predictedIndex": 99.9001
    },
    {
      "time": "2026-07-13T10:00:00Z",
      "actualIndex": 99.9179,
      "predictedIndex": 100.0379
    },
    {
      "time": "2026-07-13T11:00:00Z",
      "actualIndex": 99.541,
      "predictedIndex": 99.9216
    },
    {
      "time": "2026-07-13T12:00:00Z",
      "actualIndex": 99.455,
      "predictedIndex": 99.5446
    },
    {
      "time": "2026-07-13T13:00:00Z",
      "actualIndex": 98.9603,
      "predictedIndex": 99.4585
    },
    {
      "time": "2026-07-13T14:00:00Z",
      "actualIndex": 98.7119,
      "predictedIndex": 98.9637
    },
    {
      "time": "2026-07-13T15:00:00Z",
      "actualIndex": 98.9529,
      "predictedIndex": 98.7149
    },
    {
      "time": "2026-07-13T16:00:00Z",
      "actualIndex": 98.8001,
      "predictedIndex": 98.9549
    },
    {
      "time": "2026-07-13T17:00:00Z",
      "actualIndex": 98.8426,
      "predictedIndex": 98.8012
    },
    {
      "time": "2026-07-13T18:00:00Z",
      "actualIndex": 98.819,
      "predictedIndex": 98.8429
    },
    {
      "time": "2026-07-13T19:00:00Z",
      "actualIndex": 98.8836,
      "predictedIndex": 98.8184
    },
    {
      "time": "2026-07-13T20:00:00Z",
      "actualIndex": 98.9321,
      "predictedIndex": 98.8821
    },
    {
      "time": "2026-07-13T21:00:00Z",
      "actualIndex": 98.8902,
      "predictedIndex": 98.93
    },
    {
      "time": "2026-07-13T22:00:00Z",
      "actualIndex": 98.8349,
      "predictedIndex": 98.888
    },
    {
      "time": "2026-07-13T23:00:00Z",
      "actualIndex": 98.7947,
      "predictedIndex": 98.8325
    },
    {
      "time": "2026-07-14T00:00:00Z",
      "actualIndex": 98.2218,
      "predictedIndex": 98.7921
    },
    {
      "time": "2026-07-14T01:00:00Z",
      "actualIndex": 98.5539,
      "predictedIndex": 98.219
    },
    {
      "time": "2026-07-14T02:00:00Z",
      "actualIndex": 98.3921,
      "predictedIndex": 98.5501
    },
    {
      "time": "2026-07-14T03:00:00Z",
      "actualIndex": 98.3458,
      "predictedIndex": 98.3876
    },
    {
      "time": "2026-07-14T04:00:00Z",
      "actualIndex": 98.3932,
      "predictedIndex": 98.3414
    },
    {
      "time": "2026-07-14T05:00:00Z",
      "actualIndex": 98.7259,
      "predictedIndex": 98.389
    },
    {
      "time": "2026-07-14T06:00:00Z",
      "actualIndex": 99.3619,
      "predictedIndex": 98.7215
    },
    {
      "time": "2026-07-14T07:00:00Z",
      "actualIndex": 99.3708,
      "predictedIndex": 99.3574
    },
    {
      "time": "2026-07-14T08:00:00Z",
      "actualIndex": 98.95,
      "predictedIndex": 99.3658
    },
    {
      "time": "2026-07-14T09:00:00Z",
      "actualIndex": 98.6797,
      "predictedIndex": 98.9441
    },
    {
      "time": "2026-07-14T10:00:00Z",
      "actualIndex": 99.0427,
      "predictedIndex": 98.6728
    },
    {
      "time": "2026-07-14T11:00:00Z",
      "actualIndex": 98.7425,
      "predictedIndex": 99.0348
    },
    {
      "time": "2026-07-14T12:00:00Z",
      "actualIndex": 98.7351,
      "predictedIndex": 98.7337
    },
    {
      "time": "2026-07-14T13:00:00Z",
      "actualIndex": 99.0185,
      "predictedIndex": 98.7255
    },
    {
      "time": "2026-07-14T14:00:00Z",
      "actualIndex": 98.7764,
      "predictedIndex": 99.0078
    },
    {
      "time": "2026-07-14T15:00:00Z",
      "actualIndex": 98.853,
      "predictedIndex": 98.7651
    },
    {
      "time": "2026-07-14T16:00:00Z",
      "actualIndex": 98.9681,
      "predictedIndex": 98.8417
    },
    {
      "time": "2026-07-14T17:00:00Z",
      "actualIndex": 98.8348,
      "predictedIndex": 98.9563
    },
    {
      "time": "2026-07-14T18:00:00Z",
      "actualIndex": 98.8171,
      "predictedIndex": 98.8232
    },
    {
      "time": "2026-07-14T19:00:00Z",
      "actualIndex": 98.9253,
      "predictedIndex": 98.8055
    },
    {
      "time": "2026-07-14T20:00:00Z",
      "actualIndex": 99.0338,
      "predictedIndex": 98.9136
    },
    {
      "time": "2026-07-14T21:00:00Z",
      "actualIndex": 98.9782,
      "predictedIndex": 99.0221
    },
    {
      "time": "2026-07-14T22:00:00Z",
      "actualIndex": 99.0233,
      "predictedIndex": 98.9664
    },
    {
      "time": "2026-07-14T23:00:00Z",
      "actualIndex": 99.0286,
      "predictedIndex": 99.0115
    },
    {
      "time": "2026-07-15T00:00:00Z",
      "actualIndex": 98.9711,
      "predictedIndex": 99.017
    },
    {
      "time": "2026-07-15T01:00:00Z",
      "actualIndex": 99.0103,
      "predictedIndex": 98.9598
    },
    {
      "time": "2026-07-15T02:00:00Z",
      "actualIndex": 98.7656,
      "predictedIndex": 98.9988
    },
    {
      "time": "2026-07-15T03:00:00Z",
      "actualIndex": 98.7157,
      "predictedIndex": 98.7546
    },
    {
      "time": "2026-07-15T04:00:00Z",
      "actualIndex": 98.8198,
      "predictedIndex": 98.7054
    },
    {
      "time": "2026-07-15T05:00:00Z",
      "actualIndex": 98.8671,
      "predictedIndex": 98.8108
    },
    {
      "time": "2026-07-15T06:00:00Z",
      "actualIndex": 98.8596,
      "predictedIndex": 98.8592
    },
    {
      "time": "2026-07-15T07:00:00Z",
      "actualIndex": 98.8967,
      "predictedIndex": 98.8524
    },
    {
      "time": "2026-07-15T08:00:00Z",
      "actualIndex": 99.0946,
      "predictedIndex": 98.8913
    },
    {
      "time": "2026-07-15T09:00:00Z",
      "actualIndex": 98.9737,
      "predictedIndex": 99.0901
    },
    {
      "time": "2026-07-15T10:00:00Z",
      "actualIndex": 99.0843,
      "predictedIndex": 98.97
    },
    {
      "time": "2026-07-15T11:00:00Z",
      "actualIndex": 99.1928,
      "predictedIndex": 99.0817
    },
    {
      "time": "2026-07-15T12:00:00Z",
      "actualIndex": 99.1169,
      "predictedIndex": 99.1915
    },
    {
      "time": "2026-07-15T13:00:00Z",
      "actualIndex": 99.237,
      "predictedIndex": 99.1168
    },
    {
      "time": "2026-07-15T14:00:00Z",
      "actualIndex": 99.119,
      "predictedIndex": 99.2375
    },
    {
      "time": "2026-07-15T15:00:00Z",
      "actualIndex": 99.0623,
      "predictedIndex": 99.1197
    },
    {
      "time": "2026-07-15T16:00:00Z",
      "actualIndex": null,
      "predictedIndex": 99.0636
    },
    {
      "time": "2026-07-15T17:00:00Z",
      "actualIndex": null,
      "predictedIndex": 99.0634
    },
    {
      "time": "2026-07-15T18:00:00Z",
      "actualIndex": null,
      "predictedIndex": 99.0644
    },
    {
      "time": "2026-07-15T19:00:00Z",
      "actualIndex": null,
      "predictedIndex": 99.0651
    },
    {
      "time": "2026-07-15T20:00:00Z",
      "actualIndex": null,
      "predictedIndex": 99.0649
    },
    {
      "time": "2026-07-15T21:00:00Z",
      "actualIndex": null,
      "predictedIndex": 99.061
    },
    {
      "time": "2026-07-15T22:00:00Z",
      "actualIndex": null,
      "predictedIndex": 99.0563
    },
    {
      "time": "2026-07-15T23:00:00Z",
      "actualIndex": null,
      "predictedIndex": 99.0554
    },
    {
      "time": "2026-07-16T00:00:00Z",
      "actualIndex": null,
      "predictedIndex": 99.0515
    },
    {
      "time": "2026-07-16T01:00:00Z",
      "actualIndex": null,
      "predictedIndex": 99.0493
    },
    {
      "time": "2026-07-16T02:00:00Z",
      "actualIndex": null,
      "predictedIndex": 99.0461
    },
    {
      "time": "2026-07-16T03:00:00Z",
      "actualIndex": null,
      "predictedIndex": 99.0434
    },
    {
      "time": "2026-07-16T04:00:00Z",
      "actualIndex": null,
      "predictedIndex": 99.0405
    },
    {
      "time": "2026-07-16T05:00:00Z",
      "actualIndex": null,
      "predictedIndex": 99.0409
    },
    {
      "time": "2026-07-16T06:00:00Z",
      "actualIndex": null,
      "predictedIndex": 99.04
    },
    {
      "time": "2026-07-16T07:00:00Z",
      "actualIndex": null,
      "predictedIndex": 99.0381
    },
    {
      "time": "2026-07-16T08:00:00Z",
      "actualIndex": null,
      "predictedIndex": 99.0383
    },
    {
      "time": "2026-07-16T09:00:00Z",
      "actualIndex": null,
      "predictedIndex": 99.0383
    },
    {
      "time": "2026-07-16T10:00:00Z",
      "actualIndex": null,
      "predictedIndex": 99.0369
    },
    {
      "time": "2026-07-16T11:00:00Z",
      "actualIndex": null,
      "predictedIndex": 99.0391
    },
    {
      "time": "2026-07-16T12:00:00Z",
      "actualIndex": null,
      "predictedIndex": 99.0407
    },
    {
      "time": "2026-07-16T13:00:00Z",
      "actualIndex": null,
      "predictedIndex": 99.0418
    },
    {
      "time": "2026-07-16T14:00:00Z",
      "actualIndex": null,
      "predictedIndex": 99.0395
    },
    {
      "time": "2026-07-16T15:00:00Z",
      "actualIndex": null,
      "predictedIndex": 99.0378
    }
  ],
  "signal": {
    "direction": "flat",
    "changePercent24h": -0.7124,
    "confidence": 0.942
  },
  "commentary": {
    "en": "HTX-DAO is expected to remain flat in the next 24 hours with a predicted return of -0.0% due to neutral RSI and mid-band Bollinger Band %B. The recent news on Bitcoin's price increase and regulatory updates in Japan may have a limited impact on HTX-DAO's price movement. The overall crypto market remains in an extreme fear state.",
    "ja": "HTX-DAOは、次の24時間に-0.0%の予想リターンでフラットを維持する可能性があり、RSIが中立的でボリンジャーバンドの%Bが中間の値を示しているためです。ビットコインの価格上昇や日本の規制更新などの最近のニュースはHTX-DAOの価格動向に限りなく影響を与える可能性はあります。総合的な暗号通貨市場は極度の恐怖の状態を維持しています。",
    "sources": [
      {
        "label": "Fear & Greed Index",
        "value": "25 — Extreme Fear",
        "url": "https://alternative.me/crypto/fear-and-greed-index/"
      },
      {
        "label": "RSI-14",
        "value": "51.6 (neutral)",
        "url": "https://www.coingecko.com/en/coins/htx-dao"
      },
      {
        "label": "Bollinger Band %B",
        "value": "0.63 (mid range)",
        "url": null
      },
      {
        "label": "Volume (24 h ratio)",
        "value": "1.1× average",
        "url": null
      },
      {
        "label": "BTC 24 h return",
        "value": "+0.00%",
        "url": "https://www.coingecko.com/en/coins/bitcoin"
      },
      {
        "label": "Crypto market cap (24 h)",
        "value": "+1.64%",
        "url": "https://www.coingecko.com/en/global-charts"
      },
      {
        "label": "CoinGecko Community Sentiment",
        "value": "100% bullish",
        "url": "https://www.coingecko.com/en/coins/htx-dao"
      },
      {
        "label": "CoinTelegraph",
        "value": "Bitcoin hits $65.5K as more surprise US inflation data sparks three-week BTC price high",
        "url": "https://cointelegraph.com/markets/bitcoin-hits-655k-as-more-surprise-us-inflation-data-sparks-three-week-btc-price-high?utm_source=rss_feed&utm_medium=rss&utm_campaign=rss_partner_inbound"
      },
      {
        "label": "CoinTelegraph",
        "value": "Is Robinhood Chain’s success bullish or bearish for ETH the asset?",
        "url": "https://cointelegraph.com/features/has-robinhoods-layer-2-given-eth-a-new-bull-case?utm_source=rss_feed&utm_medium=rss&utm_campaign=rss_partner_inbound"
      },
      {
        "label": "CoinTelegraph",
        "value": "Here’s what happened in crypto today",
        "url": "https://cointelegraph.com/news/what-happened-in-crypto-today?utm_source=rss_feed&utm_medium=rss&utm_campaign=rss_partner_inbound"
      }
    ]
  }
}