{
  "coinId": "rain",
  "generatedAt": "2026-07-05T21:00:06.102287Z",
  "modelVersion": "lstm-2.0.0",
  "series": [
    {
      "time": "2026-06-28T22:00:00Z",
      "actualIndex": 100.0,
      "predictedIndex": 100.0
    },
    {
      "time": "2026-06-28T23:00:00Z",
      "actualIndex": 99.9424,
      "predictedIndex": 99.995
    },
    {
      "time": "2026-06-29T00:00:00Z",
      "actualIndex": 100.1543,
      "predictedIndex": 99.9296
    },
    {
      "time": "2026-06-29T01:00:00Z",
      "actualIndex": 100.1968,
      "predictedIndex": 100.1388
    },
    {
      "time": "2026-06-29T02:00:00Z",
      "actualIndex": 100.2219,
      "predictedIndex": 100.1787
    },
    {
      "time": "2026-06-29T03:00:00Z",
      "actualIndex": 100.2574,
      "predictedIndex": 100.2004
    },
    {
      "time": "2026-06-29T04:00:00Z",
      "actualIndex": 100.1422,
      "predictedIndex": 100.2355
    },
    {
      "time": "2026-06-29T05:00:00Z",
      "actualIndex": 100.0412,
      "predictedIndex": 100.1246
    },
    {
      "time": "2026-06-29T06:00:00Z",
      "actualIndex": 100.3206,
      "predictedIndex": 100.0222
    },
    {
      "time": "2026-06-29T07:00:00Z",
      "actualIndex": 100.2925,
      "predictedIndex": 100.3005
    },
    {
      "time": "2026-06-29T08:00:00Z",
      "actualIndex": 100.035,
      "predictedIndex": 100.2713
    },
    {
      "time": "2026-06-29T09:00:00Z",
      "actualIndex": 100.0111,
      "predictedIndex": 100.0124
    },
    {
      "time": "2026-06-29T10:00:00Z",
      "actualIndex": 100.1181,
      "predictedIndex": 99.9867
    },
    {
      "time": "2026-06-29T11:00:00Z",
      "actualIndex": 99.9703,
      "predictedIndex": 100.0923
    },
    {
      "time": "2026-06-29T12:00:00Z",
      "actualIndex": 99.8845,
      "predictedIndex": 99.9458
    },
    {
      "time": "2026-06-29T13:00:00Z",
      "actualIndex": 100.0487,
      "predictedIndex": 99.862
    },
    {
      "time": "2026-06-29T14:00:00Z",
      "actualIndex": 99.8858,
      "predictedIndex": 100.0277
    },
    {
      "time": "2026-06-29T15:00:00Z",
      "actualIndex": 99.8509,
      "predictedIndex": 99.8665
    },
    {
      "time": "2026-06-29T16:00:00Z",
      "actualIndex": 102.9371,
      "predictedIndex": 99.8333
    },
    {
      "time": "2026-06-29T17:00:00Z",
      "actualIndex": 102.5054,
      "predictedIndex": 102.9186
    },
    {
      "time": "2026-06-29T18:00:00Z",
      "actualIndex": 103.1521,
      "predictedIndex": 102.4868
    },
    {
      "time": "2026-06-29T19:00:00Z",
      "actualIndex": 102.6742,
      "predictedIndex": 103.1334
    },
    {
      "time": "2026-06-29T20:00:00Z",
      "actualIndex": 102.7293,
      "predictedIndex": 102.6564
    },
    {
      "time": "2026-06-29T21:00:00Z",
      "actualIndex": 102.4343,
      "predictedIndex": 102.7128
    },
    {
      "time": "2026-06-29T22:00:00Z",
      "actualIndex": 102.5873,
      "predictedIndex": 102.4168
    },
    {
      "time": "2026-06-29T23:00:00Z",
      "actualIndex": 102.5467,
      "predictedIndex": 102.5696
    },
    {
      "time": "2026-06-30T00:00:00Z",
      "actualIndex": 102.6778,
      "predictedIndex": 102.5275
    },
    {
      "time": "2026-06-30T01:00:00Z",
      "actualIndex": 102.5959,
      "predictedIndex": 102.6585
    },
    {
      "time": "2026-06-30T02:00:00Z",
      "actualIndex": 102.5224,
      "predictedIndex": 102.5758
    },
    {
      "time": "2026-06-30T03:00:00Z",
      "actualIndex": 102.5845,
      "predictedIndex": 102.5025
    },
    {
      "time": "2026-06-30T04:00:00Z",
      "actualIndex": 102.417,
      "predictedIndex": 102.565
    },
    {
      "time": "2026-06-30T05:00:00Z",
      "actualIndex": 102.3331,
      "predictedIndex": 102.3975
    },
    {
      "time": "2026-06-30T06:00:00Z",
      "actualIndex": 102.2623,
      "predictedIndex": 102.3141
    },
    {
      "time": "2026-06-30T07:00:00Z",
      "actualIndex": 102.1712,
      "predictedIndex": 102.2445
    },
    {
      "time": "2026-06-30T08:00:00Z",
      "actualIndex": 102.0025,
      "predictedIndex": 102.1543
    },
    {
      "time": "2026-06-30T09:00:00Z",
      "actualIndex": 101.8106,
      "predictedIndex": 101.9861
    },
    {
      "time": "2026-06-30T10:00:00Z",
      "actualIndex": 101.5382,
      "predictedIndex": 101.7945
    },
    {
      "time": "2026-06-30T11:00:00Z",
      "actualIndex": 101.4367,
      "predictedIndex": 101.5232
    },
    {
      "time": "2026-06-30T12:00:00Z",
      "actualIndex": 101.3843,
      "predictedIndex": 101.4233
    },
    {
      "time": "2026-06-30T13:00:00Z",
      "actualIndex": 101.0164,
      "predictedIndex": 101.3717
    },
    {
      "time": "2026-06-30T14:00:00Z",
      "actualIndex": 101.261,
      "predictedIndex": 101.0049
    },
    {
      "time": "2026-06-30T15:00:00Z",
      "actualIndex": 101.1654,
      "predictedIndex": 101.2502
    },
    {
      "time": "2026-06-30T16:00:00Z",
      "actualIndex": 101.2127,
      "predictedIndex": 101.1551
    },
    {
      "time": "2026-06-30T17:00:00Z",
      "actualIndex": 101.2914,
      "predictedIndex": 101.2025
    },
    {
      "time": "2026-06-30T18:00:00Z",
      "actualIndex": 101.2689,
      "predictedIndex": 101.2808
    },
    {
      "time": "2026-06-30T19:00:00Z",
      "actualIndex": 101.3143,
      "predictedIndex": 101.2581
    },
    {
      "time": "2026-06-30T20:00:00Z",
      "actualIndex": 101.3194,
      "predictedIndex": 101.3039
    },
    {
      "time": "2026-06-30T21:00:00Z",
      "actualIndex": 101.3009,
      "predictedIndex": 101.3091
    },
    {
      "time": "2026-06-30T22:00:00Z",
      "actualIndex": 101.3981,
      "predictedIndex": 101.2914
    },
    {
      "time": "2026-06-30T23:00:00Z",
      "actualIndex": 101.164,
      "predictedIndex": 101.3881
    },
    {
      "time": "2026-07-01T00:00:00Z",
      "actualIndex": 101.2584,
      "predictedIndex": 101.1537
    },
    {
      "time": "2026-07-01T01:00:00Z",
      "actualIndex": 101.5031,
      "predictedIndex": 101.2478
    },
    {
      "time": "2026-07-01T02:00:00Z",
      "actualIndex": 101.4427,
      "predictedIndex": 101.4926
    },
    {
      "time": "2026-07-01T03:00:00Z",
      "actualIndex": 101.6604,
      "predictedIndex": 101.4327
    },
    {
      "time": "2026-07-01T04:00:00Z",
      "actualIndex": 101.1898,
      "predictedIndex": 101.6507
    },
    {
      "time": "2026-07-01T05:00:00Z",
      "actualIndex": 100.8609,
      "predictedIndex": 101.1804
    },
    {
      "time": "2026-07-01T06:00:00Z",
      "actualIndex": 100.6342,
      "predictedIndex": 100.8519
    },
    {
      "time": "2026-07-01T07:00:00Z",
      "actualIndex": 100.3729,
      "predictedIndex": 100.6264
    },
    {
      "time": "2026-07-01T08:00:00Z",
      "actualIndex": 100.2226,
      "predictedIndex": 100.3669
    },
    {
      "time": "2026-07-01T09:00:00Z",
      "actualIndex": 100.433,
      "predictedIndex": 100.218
    },
    {
      "time": "2026-07-01T10:00:00Z",
      "actualIndex": 100.4903,
      "predictedIndex": 100.4296
    },
    {
      "time": "2026-07-01T11:00:00Z",
      "actualIndex": 100.0601,
      "predictedIndex": 100.4884
    },
    {
      "time": "2026-07-01T12:00:00Z",
      "actualIndex": 99.9846,
      "predictedIndex": 100.0596
    },
    {
      "time": "2026-07-01T13:00:00Z",
      "actualIndex": 99.9201,
      "predictedIndex": 99.9852
    },
    {
      "time": "2026-07-01T14:00:00Z",
      "actualIndex": 100.3451,
      "predictedIndex": 99.9217
    },
    {
      "time": "2026-07-01T15:00:00Z",
      "actualIndex": 100.3958,
      "predictedIndex": 100.3465
    },
    {
      "time": "2026-07-01T16:00:00Z",
      "actualIndex": 100.3926,
      "predictedIndex": 100.3969
    },
    {
      "time": "2026-07-01T17:00:00Z",
      "actualIndex": 100.2507,
      "predictedIndex": 100.3955
    },
    {
      "time": "2026-07-01T18:00:00Z",
      "actualIndex": 100.3689,
      "predictedIndex": 100.2534
    },
    {
      "time": "2026-07-01T19:00:00Z",
      "actualIndex": 100.2658,
      "predictedIndex": 100.3709
    },
    {
      "time": "2026-07-01T20:00:00Z",
      "actualIndex": 100.3046,
      "predictedIndex": 100.2673
    },
    {
      "time": "2026-07-01T21:00:00Z",
      "actualIndex": 99.9279,
      "predictedIndex": 100.3055
    },
    {
      "time": "2026-07-01T22:00:00Z",
      "actualIndex": 100.4799,
      "predictedIndex": 99.9284
    },
    {
      "time": "2026-07-01T23:00:00Z",
      "actualIndex": 100.0766,
      "predictedIndex": 100.4802
    },
    {
      "time": "2026-07-02T00:00:00Z",
      "actualIndex": 99.9834,
      "predictedIndex": 100.0768
    },
    {
      "time": "2026-07-02T01:00:00Z",
      "actualIndex": 99.9928,
      "predictedIndex": 99.9836
    },
    {
      "time": "2026-07-02T02:00:00Z",
      "actualIndex": 100.0931,
      "predictedIndex": 99.9935
    },
    {
      "time": "2026-07-02T03:00:00Z",
      "actualIndex": 100.1262,
      "predictedIndex": 100.094
    },
    {
      "time": "2026-07-02T04:00:00Z",
      "actualIndex": 100.2678,
      "predictedIndex": 100.1273
    },
    {
      "time": "2026-07-02T05:00:00Z",
      "actualIndex": 100.1581,
      "predictedIndex": 100.2694
    },
    {
      "time": "2026-07-02T06:00:00Z",
      "actualIndex": 100.0778,
      "predictedIndex": 100.1598
    },
    {
      "time": "2026-07-02T07:00:00Z",
      "actualIndex": 100.04,
      "predictedIndex": 100.0795
    },
    {
      "time": "2026-07-02T08:00:00Z",
      "actualIndex": 99.7422,
      "predictedIndex": 100.0416
    },
    {
      "time": "2026-07-02T09:00:00Z",
      "actualIndex": 99.2565,
      "predictedIndex": 99.7443
    },
    {
      "time": "2026-07-02T10:00:00Z",
      "actualIndex": 99.6649,
      "predictedIndex": 99.259
    },
    {
      "time": "2026-07-02T11:00:00Z",
      "actualIndex": 99.2674,
      "predictedIndex": 99.6676
    },
    {
      "time": "2026-07-02T12:00:00Z",
      "actualIndex": 99.3591,
      "predictedIndex": 99.2701
    },
    {
      "time": "2026-07-02T13:00:00Z",
      "actualIndex": 99.7682,
      "predictedIndex": 99.3618
    },
    {
      "time": "2026-07-02T14:00:00Z",
      "actualIndex": 100.1985,
      "predictedIndex": 99.7704
    },
    {
      "time": "2026-07-02T15:00:00Z",
      "actualIndex": 99.7199,
      "predictedIndex": 100.2
    },
    {
      "time": "2026-07-02T16:00:00Z",
      "actualIndex": 99.6793,
      "predictedIndex": 99.7216
    },
    {
      "time": "2026-07-02T17:00:00Z",
      "actualIndex": 99.8065,
      "predictedIndex": 99.681
    },
    {
      "time": "2026-07-02T18:00:00Z",
      "actualIndex": 99.7041,
      "predictedIndex": 99.8083
    },
    {
      "time": "2026-07-02T19:00:00Z",
      "actualIndex": 99.7892,
      "predictedIndex": 99.7061
    },
    {
      "time": "2026-07-02T20:00:00Z",
      "actualIndex": 99.7385,
      "predictedIndex": 99.7914
    },
    {
      "time": "2026-07-02T21:00:00Z",
      "actualIndex": 99.9066,
      "predictedIndex": 99.7409
    },
    {
      "time": "2026-07-02T22:00:00Z",
      "actualIndex": 99.751,
      "predictedIndex": 99.9092
    },
    {
      "time": "2026-07-02T23:00:00Z",
      "actualIndex": 99.9132,
      "predictedIndex": 99.7538
    },
    {
      "time": "2026-07-03T00:00:00Z",
      "actualIndex": 99.917,
      "predictedIndex": 99.9161
    },
    {
      "time": "2026-07-03T01:00:00Z",
      "actualIndex": 99.8658,
      "predictedIndex": 99.92
    },
    {
      "time": "2026-07-03T02:00:00Z",
      "actualIndex": 100.4752,
      "predictedIndex": 99.8687
    },
    {
      "time": "2026-07-03T03:00:00Z",
      "actualIndex": 99.9595,
      "predictedIndex": 100.4782
    },
    {
      "time": "2026-07-03T04:00:00Z",
      "actualIndex": 99.8871,
      "predictedIndex": 99.9622
    },
    {
      "time": "2026-07-03T05:00:00Z",
      "actualIndex": 99.8803,
      "predictedIndex": 99.8891
    },
    {
      "time": "2026-07-03T06:00:00Z",
      "actualIndex": 100.1804,
      "predictedIndex": 99.8813
    },
    {
      "time": "2026-07-03T07:00:00Z",
      "actualIndex": 100.2316,
      "predictedIndex": 100.1807
    },
    {
      "time": "2026-07-03T08:00:00Z",
      "actualIndex": 100.1002,
      "predictedIndex": 100.2315
    },
    {
      "time": "2026-07-03T09:00:00Z",
      "actualIndex": 99.9251,
      "predictedIndex": 100.0997
    },
    {
      "time": "2026-07-03T10:00:00Z",
      "actualIndex": 100.1834,
      "predictedIndex": 99.9242
    },
    {
      "time": "2026-07-03T11:00:00Z",
      "actualIndex": 100.2583,
      "predictedIndex": 100.1818
    },
    {
      "time": "2026-07-03T12:00:00Z",
      "actualIndex": 100.0516,
      "predictedIndex": 100.2568
    },
    {
      "time": "2026-07-03T13:00:00Z",
      "actualIndex": 99.9633,
      "predictedIndex": 100.0508
    },
    {
      "time": "2026-07-03T14:00:00Z",
      "actualIndex": 100.1757,
      "predictedIndex": 99.9625
    },
    {
      "time": "2026-07-03T15:00:00Z",
      "actualIndex": 99.7258,
      "predictedIndex": 100.1751
    },
    {
      "time": "2026-07-03T16:00:00Z",
      "actualIndex": 99.5614,
      "predictedIndex": 99.725
    },
    {
      "time": "2026-07-03T17:00:00Z",
      "actualIndex": 99.4542,
      "predictedIndex": 99.5601
    },
    {
      "time": "2026-07-03T18:00:00Z",
      "actualIndex": 99.6597,
      "predictedIndex": 99.4529
    },
    {
      "time": "2026-07-03T19:00:00Z",
      "actualIndex": 99.6657,
      "predictedIndex": 99.6584
    },
    {
      "time": "2026-07-03T20:00:00Z",
      "actualIndex": 99.6088,
      "predictedIndex": 99.6644
    },
    {
      "time": "2026-07-03T21:00:00Z",
      "actualIndex": 100.0161,
      "predictedIndex": 99.6073
    },
    {
      "time": "2026-07-03T22:00:00Z",
      "actualIndex": 99.5297,
      "predictedIndex": 100.0145
    },
    {
      "time": "2026-07-03T23:00:00Z",
      "actualIndex": 99.4719,
      "predictedIndex": 99.5282
    },
    {
      "time": "2026-07-04T00:00:00Z",
      "actualIndex": 99.4875,
      "predictedIndex": 99.47
    },
    {
      "time": "2026-07-04T01:00:00Z",
      "actualIndex": 99.4286,
      "predictedIndex": 99.485
    },
    {
      "time": "2026-07-04T02:00:00Z",
      "actualIndex": 99.3532,
      "predictedIndex": 99.4261
    },
    {
      "time": "2026-07-04T03:00:00Z",
      "actualIndex": 99.447,
      "predictedIndex": 99.3516
    },
    {
      "time": "2026-07-04T04:00:00Z",
      "actualIndex": 99.4757,
      "predictedIndex": 99.4454
    },
    {
      "time": "2026-07-04T05:00:00Z",
      "actualIndex": 99.5598,
      "predictedIndex": 99.4744
    },
    {
      "time": "2026-07-04T06:00:00Z",
      "actualIndex": 99.4658,
      "predictedIndex": 99.5573
    },
    {
      "time": "2026-07-04T07:00:00Z",
      "actualIndex": 99.2577,
      "predictedIndex": 99.4611
    },
    {
      "time": "2026-07-04T08:00:00Z",
      "actualIndex": 99.3529,
      "predictedIndex": 99.2509
    },
    {
      "time": "2026-07-04T09:00:00Z",
      "actualIndex": 99.5649,
      "predictedIndex": 99.346
    },
    {
      "time": "2026-07-04T10:00:00Z",
      "actualIndex": 99.0851,
      "predictedIndex": 99.5608
    },
    {
      "time": "2026-07-04T11:00:00Z",
      "actualIndex": 99.3757,
      "predictedIndex": 99.0822
    },
    {
      "time": "2026-07-04T12:00:00Z",
      "actualIndex": 99.1342,
      "predictedIndex": 99.3714
    },
    {
      "time": "2026-07-04T13:00:00Z",
      "actualIndex": 98.869,
      "predictedIndex": 99.1287
    },
    {
      "time": "2026-07-04T14:00:00Z",
      "actualIndex": 99.1212,
      "predictedIndex": 98.863
    },
    {
      "time": "2026-07-04T15:00:00Z",
      "actualIndex": 99.2954,
      "predictedIndex": 99.1151
    },
    {
      "time": "2026-07-04T16:00:00Z",
      "actualIndex": 99.6815,
      "predictedIndex": 99.2887
    },
    {
      "time": "2026-07-04T17:00:00Z",
      "actualIndex": 99.1894,
      "predictedIndex": 99.6732
    },
    {
      "time": "2026-07-04T18:00:00Z",
      "actualIndex": 99.5754,
      "predictedIndex": 99.1803
    },
    {
      "time": "2026-07-04T19:00:00Z",
      "actualIndex": 99.2632,
      "predictedIndex": 99.5651
    },
    {
      "time": "2026-07-04T20:00:00Z",
      "actualIndex": 99.2777,
      "predictedIndex": 99.2526
    },
    {
      "time": "2026-07-04T21:00:00Z",
      "actualIndex": 99.2096,
      "predictedIndex": 99.2648
    },
    {
      "time": "2026-07-04T22:00:00Z",
      "actualIndex": 99.1217,
      "predictedIndex": 99.1968
    },
    {
      "time": "2026-07-04T23:00:00Z",
      "actualIndex": 98.9724,
      "predictedIndex": 99.1076
    },
    {
      "time": "2026-07-05T00:00:00Z",
      "actualIndex": 99.14,
      "predictedIndex": 98.9573
    },
    {
      "time": "2026-07-05T01:00:00Z",
      "actualIndex": 98.8665,
      "predictedIndex": 99.1247
    },
    {
      "time": "2026-07-05T02:00:00Z",
      "actualIndex": 98.9037,
      "predictedIndex": 98.8493
    },
    {
      "time": "2026-07-05T03:00:00Z",
      "actualIndex": 98.9206,
      "predictedIndex": 98.888
    },
    {
      "time": "2026-07-05T04:00:00Z",
      "actualIndex": 98.7746,
      "predictedIndex": 98.9037
    },
    {
      "time": "2026-07-05T05:00:00Z",
      "actualIndex": 99.0055,
      "predictedIndex": 98.7569
    },
    {
      "time": "2026-07-05T06:00:00Z",
      "actualIndex": 98.8063,
      "predictedIndex": 98.9869
    },
    {
      "time": "2026-07-05T07:00:00Z",
      "actualIndex": 98.74,
      "predictedIndex": 98.7878
    },
    {
      "time": "2026-07-05T08:00:00Z",
      "actualIndex": 98.6587,
      "predictedIndex": 98.7207
    },
    {
      "time": "2026-07-05T09:00:00Z",
      "actualIndex": 98.4972,
      "predictedIndex": 98.6381
    },
    {
      "time": "2026-07-05T10:00:00Z",
      "actualIndex": 98.6097,
      "predictedIndex": 98.475
    },
    {
      "time": "2026-07-05T11:00:00Z",
      "actualIndex": 98.6464,
      "predictedIndex": 98.5864
    },
    {
      "time": "2026-07-05T12:00:00Z",
      "actualIndex": 98.1874,
      "predictedIndex": 98.6218
    },
    {
      "time": "2026-07-05T13:00:00Z",
      "actualIndex": 98.5867,
      "predictedIndex": 98.1615
    },
    {
      "time": "2026-07-05T14:00:00Z",
      "actualIndex": 98.4834,
      "predictedIndex": 98.5595
    },
    {
      "time": "2026-07-05T15:00:00Z",
      "actualIndex": 98.5336,
      "predictedIndex": 98.4545
    },
    {
      "time": "2026-07-05T16:00:00Z",
      "actualIndex": 98.5316,
      "predictedIndex": 98.5044
    },
    {
      "time": "2026-07-05T17:00:00Z",
      "actualIndex": 98.3255,
      "predictedIndex": 98.5024
    },
    {
      "time": "2026-07-05T18:00:00Z",
      "actualIndex": 98.7241,
      "predictedIndex": 98.2969
    },
    {
      "time": "2026-07-05T19:00:00Z",
      "actualIndex": 98.7436,
      "predictedIndex": 98.695
    },
    {
      "time": "2026-07-05T20:00:00Z",
      "actualIndex": 98.3134,
      "predictedIndex": 98.7146
    },
    {
      "time": "2026-07-05T21:00:00Z",
      "actualIndex": 97.8736,
      "predictedIndex": 98.2846
    },
    {
      "time": "2026-07-05T22:00:00Z",
      "actualIndex": null,
      "predictedIndex": 97.845
    },
    {
      "time": "2026-07-05T23:00:00Z",
      "actualIndex": null,
      "predictedIndex": 97.8139
    },
    {
      "time": "2026-07-06T00:00:00Z",
      "actualIndex": null,
      "predictedIndex": 97.7821
    },
    {
      "time": "2026-07-06T01:00:00Z",
      "actualIndex": null,
      "predictedIndex": 97.7445
    },
    {
      "time": "2026-07-06T02:00:00Z",
      "actualIndex": null,
      "predictedIndex": 97.7079
    },
    {
      "time": "2026-07-06T03:00:00Z",
      "actualIndex": null,
      "predictedIndex": 97.6691
    },
    {
      "time": "2026-07-06T04:00:00Z",
      "actualIndex": null,
      "predictedIndex": 97.6342
    },
    {
      "time": "2026-07-06T05:00:00Z",
      "actualIndex": null,
      "predictedIndex": 97.5947
    },
    {
      "time": "2026-07-06T06:00:00Z",
      "actualIndex": null,
      "predictedIndex": 97.5531
    },
    {
      "time": "2026-07-06T07:00:00Z",
      "actualIndex": null,
      "predictedIndex": 97.5107
    },
    {
      "time": "2026-07-06T08:00:00Z",
      "actualIndex": null,
      "predictedIndex": 97.4639
    },
    {
      "time": "2026-07-06T09:00:00Z",
      "actualIndex": null,
      "predictedIndex": 97.4199
    },
    {
      "time": "2026-07-06T10:00:00Z",
      "actualIndex": null,
      "predictedIndex": 97.3702
    },
    {
      "time": "2026-07-06T11:00:00Z",
      "actualIndex": null,
      "predictedIndex": 97.3207
    },
    {
      "time": "2026-07-06T12:00:00Z",
      "actualIndex": null,
      "predictedIndex": 97.2786
    },
    {
      "time": "2026-07-06T13:00:00Z",
      "actualIndex": null,
      "predictedIndex": 97.2359
    },
    {
      "time": "2026-07-06T14:00:00Z",
      "actualIndex": null,
      "predictedIndex": 97.1982
    },
    {
      "time": "2026-07-06T15:00:00Z",
      "actualIndex": null,
      "predictedIndex": 97.1589
    },
    {
      "time": "2026-07-06T16:00:00Z",
      "actualIndex": null,
      "predictedIndex": 97.1159
    },
    {
      "time": "2026-07-06T17:00:00Z",
      "actualIndex": null,
      "predictedIndex": 97.0761
    },
    {
      "time": "2026-07-06T18:00:00Z",
      "actualIndex": null,
      "predictedIndex": 97.033
    },
    {
      "time": "2026-07-06T19:00:00Z",
      "actualIndex": null,
      "predictedIndex": 96.9949
    },
    {
      "time": "2026-07-06T20:00:00Z",
      "actualIndex": null,
      "predictedIndex": 96.9589
    },
    {
      "time": "2026-07-06T21:00:00Z",
      "actualIndex": null,
      "predictedIndex": 96.9225
    }
  ],
  "signal": {
    "direction": "down",
    "changePercent24h": -1.4358723443518053,
    "confidence": 0.8628
  },
  "commentary": {
    "en": "Rain (RAIN) is predicted to drop by 1.0% in the next 24 hours with a confidence level of 81%. The recent news of Binance outflows and a bearish market sentiment due to the Fear & Greed Index at 23 suggest a downward trend for Rain. The sideways short-term trend and neutral RSI-14 value indicate a stable but uncertain market.",
    "ja": "Rain (RAIN) は来る24時間で1.0%の下落が予測され、信頼度は81%です。Binanceの流出とFear & Greed Indexが23の恐怖の市場感覚により下落が予想されます。短期の傾向は横ばい、RSI-14は中立的な値を示しています。",
    "sources": [
      {
        "label": "Fear & Greed Index",
        "value": "23 — Extreme Fear",
        "url": "https://alternative.me/crypto/fear-and-greed-index/"
      },
      {
        "label": "RSI-14",
        "value": "34.8 (neutral)",
        "url": "https://www.coingecko.com/en/coins/rain"
      },
      {
        "label": "Bollinger Band %B",
        "value": "-0.18 (near lower)",
        "url": null
      },
      {
        "label": "Volume (24 h ratio)",
        "value": "1.1× average",
        "url": null
      },
      {
        "label": "BTC 24 h return",
        "value": "-0.81%",
        "url": "https://www.coingecko.com/en/coins/bitcoin"
      },
      {
        "label": "Crypto market cap (24 h)",
        "value": "-0.65%",
        "url": "https://www.coingecko.com/en/global-charts"
      },
      {
        "label": "CoinGecko Community Sentiment",
        "value": "71% bullish",
        "url": "https://www.coingecko.com/en/coins/rain"
      },
      {
        "label": "CoinTelegraph",
        "value": "Bitcoin nears $63.5K into weekly close as trader warns of 'terrible' Monday",
        "url": "https://cointelegraph.com/markets/bitcoin-nears-635k-into-weekly-close-as-trader-warns-of-terrible-monday?utm_source=rss_feed&utm_medium=rss&utm_campaign=rss_partner_inbound"
      },
      {
        "label": "CoinTelegraph",
        "value": "South Africa proposes crypto tax guidance under existing framework",
        "url": "https://cointelegraph.com/news/south-africa-proposes-crypto-tax-draft-guidance?utm_source=rss_feed&utm_medium=rss&utm_campaign=rss_partner_inbound"
      },
      {
        "label": "CoinTelegraph",
        "value": "Binance outflows triple to $1.2B as ETH withdrawals hit 3-year high",
        "url": "https://cointelegraph.com/news/binance-outflows-1-23-billion-eth-withdrawals-3-year-high?utm_source=rss_feed&utm_medium=rss&utm_campaign=rss_partner_inbound"
      }
    ]
  }
}