{
  "coinId": "stellar",
  "generatedAt": "2026-06-19T21:00:08.585419Z",
  "modelVersion": "lstm-2.0.0",
  "series": [
    {
      "time": "2026-06-12T22:00:00Z",
      "actualIndex": 100.0,
      "predictedIndex": 100.0
    },
    {
      "time": "2026-06-12T23:00:00Z",
      "actualIndex": 99.7145,
      "predictedIndex": 99.9874
    },
    {
      "time": "2026-06-13T00:00:00Z",
      "actualIndex": 99.6925,
      "predictedIndex": 99.7003
    },
    {
      "time": "2026-06-13T01:00:00Z",
      "actualIndex": 99.3699,
      "predictedIndex": 99.677
    },
    {
      "time": "2026-06-13T02:00:00Z",
      "actualIndex": 99.7885,
      "predictedIndex": 99.3532
    },
    {
      "time": "2026-06-13T03:00:00Z",
      "actualIndex": 97.9898,
      "predictedIndex": 99.7705
    },
    {
      "time": "2026-06-13T04:00:00Z",
      "actualIndex": 98.4879,
      "predictedIndex": 97.9699
    },
    {
      "time": "2026-06-13T05:00:00Z",
      "actualIndex": 98.4126,
      "predictedIndex": 98.4661
    },
    {
      "time": "2026-06-13T06:00:00Z",
      "actualIndex": 98.1429,
      "predictedIndex": 98.3889
    },
    {
      "time": "2026-06-13T07:00:00Z",
      "actualIndex": 99.2342,
      "predictedIndex": 98.1184
    },
    {
      "time": "2026-06-13T08:00:00Z",
      "actualIndex": 100.8357,
      "predictedIndex": 99.2087
    },
    {
      "time": "2026-06-13T09:00:00Z",
      "actualIndex": 100.6835,
      "predictedIndex": 100.8091
    },
    {
      "time": "2026-06-13T10:00:00Z",
      "actualIndex": 101.0817,
      "predictedIndex": 100.6566
    },
    {
      "time": "2026-06-13T11:00:00Z",
      "actualIndex": 101.092,
      "predictedIndex": 101.0546
    },
    {
      "time": "2026-06-13T12:00:00Z",
      "actualIndex": 101.2408,
      "predictedIndex": 101.0652
    },
    {
      "time": "2026-06-13T13:00:00Z",
      "actualIndex": 100.9907,
      "predictedIndex": 101.2136
    },
    {
      "time": "2026-06-13T14:00:00Z",
      "actualIndex": 99.9619,
      "predictedIndex": 100.9639
    },
    {
      "time": "2026-06-13T15:00:00Z",
      "actualIndex": 100.1549,
      "predictedIndex": 99.9353
    },
    {
      "time": "2026-06-13T16:00:00Z",
      "actualIndex": 101.1331,
      "predictedIndex": 100.128
    },
    {
      "time": "2026-06-13T17:00:00Z",
      "actualIndex": 99.7659,
      "predictedIndex": 101.106
    },
    {
      "time": "2026-06-13T18:00:00Z",
      "actualIndex": 99.0635,
      "predictedIndex": 99.7385
    },
    {
      "time": "2026-06-13T19:00:00Z",
      "actualIndex": 99.1051,
      "predictedIndex": 99.0349
    },
    {
      "time": "2026-06-13T20:00:00Z",
      "actualIndex": 99.2487,
      "predictedIndex": 99.0746
    },
    {
      "time": "2026-06-13T21:00:00Z",
      "actualIndex": 98.9983,
      "predictedIndex": 99.2172
    },
    {
      "time": "2026-06-13T22:00:00Z",
      "actualIndex": 100.0158,
      "predictedIndex": 98.9656
    },
    {
      "time": "2026-06-13T23:00:00Z",
      "actualIndex": 99.3112,
      "predictedIndex": 99.9816
    },
    {
      "time": "2026-06-14T00:00:00Z",
      "actualIndex": 99.154,
      "predictedIndex": 99.2758
    },
    {
      "time": "2026-06-14T01:00:00Z",
      "actualIndex": 99.0764,
      "predictedIndex": 99.1171
    },
    {
      "time": "2026-06-14T02:00:00Z",
      "actualIndex": 100.0542,
      "predictedIndex": 99.0382
    },
    {
      "time": "2026-06-14T03:00:00Z",
      "actualIndex": 99.0439,
      "predictedIndex": 100.0156
    },
    {
      "time": "2026-06-14T04:00:00Z",
      "actualIndex": 98.5164,
      "predictedIndex": 99.006
    },
    {
      "time": "2026-06-14T05:00:00Z",
      "actualIndex": 98.3879,
      "predictedIndex": 98.4793
    },
    {
      "time": "2026-06-14T06:00:00Z",
      "actualIndex": 98.657,
      "predictedIndex": 98.3522
    },
    {
      "time": "2026-06-14T07:00:00Z",
      "actualIndex": 98.8761,
      "predictedIndex": 98.6239
    },
    {
      "time": "2026-06-14T08:00:00Z",
      "actualIndex": 98.8746,
      "predictedIndex": 98.8473
    },
    {
      "time": "2026-06-14T09:00:00Z",
      "actualIndex": 99.0048,
      "predictedIndex": 98.8487
    },
    {
      "time": "2026-06-14T10:00:00Z",
      "actualIndex": 98.5929,
      "predictedIndex": 98.9803
    },
    {
      "time": "2026-06-14T11:00:00Z",
      "actualIndex": 97.6495,
      "predictedIndex": 98.5692
    },
    {
      "time": "2026-06-14T12:00:00Z",
      "actualIndex": 97.7624,
      "predictedIndex": 97.6271
    },
    {
      "time": "2026-06-14T13:00:00Z",
      "actualIndex": 96.9512,
      "predictedIndex": 97.7406
    },
    {
      "time": "2026-06-14T14:00:00Z",
      "actualIndex": 97.1107,
      "predictedIndex": 96.9301
    },
    {
      "time": "2026-06-14T15:00:00Z",
      "actualIndex": 96.4369,
      "predictedIndex": 97.091
    },
    {
      "time": "2026-06-14T16:00:00Z",
      "actualIndex": 96.4207,
      "predictedIndex": 96.4162
    },
    {
      "time": "2026-06-14T17:00:00Z",
      "actualIndex": 96.9059,
      "predictedIndex": 96.4004
    },
    {
      "time": "2026-06-14T18:00:00Z",
      "actualIndex": 96.3329,
      "predictedIndex": 96.8853
    },
    {
      "time": "2026-06-14T19:00:00Z",
      "actualIndex": 96.4339,
      "predictedIndex": 96.3127
    },
    {
      "time": "2026-06-14T20:00:00Z",
      "actualIndex": 96.2719,
      "predictedIndex": 96.4146
    },
    {
      "time": "2026-06-14T21:00:00Z",
      "actualIndex": 96.8248,
      "predictedIndex": 96.2528
    },
    {
      "time": "2026-06-14T22:00:00Z",
      "actualIndex": 99.7357,
      "predictedIndex": 96.8066
    },
    {
      "time": "2026-06-14T23:00:00Z",
      "actualIndex": 99.562,
      "predictedIndex": 99.7189
    },
    {
      "time": "2026-06-15T00:00:00Z",
      "actualIndex": 101.5223,
      "predictedIndex": 99.546
    },
    {
      "time": "2026-06-15T01:00:00Z",
      "actualIndex": 100.5035,
      "predictedIndex": 101.5072
    },
    {
      "time": "2026-06-15T02:00:00Z",
      "actualIndex": 99.9819,
      "predictedIndex": 100.4893
    },
    {
      "time": "2026-06-15T03:00:00Z",
      "actualIndex": 100.1402,
      "predictedIndex": 99.966
    },
    {
      "time": "2026-06-15T04:00:00Z",
      "actualIndex": 100.698,
      "predictedIndex": 100.1264
    },
    {
      "time": "2026-06-15T05:00:00Z",
      "actualIndex": 99.7453,
      "predictedIndex": 100.6806
    },
    {
      "time": "2026-06-15T06:00:00Z",
      "actualIndex": 100.108,
      "predictedIndex": 99.7255
    },
    {
      "time": "2026-06-15T07:00:00Z",
      "actualIndex": 100.8019,
      "predictedIndex": 100.0875
    },
    {
      "time": "2026-06-15T08:00:00Z",
      "actualIndex": 100.263,
      "predictedIndex": 100.7784
    },
    {
      "time": "2026-06-15T09:00:00Z",
      "actualIndex": 100.8128,
      "predictedIndex": 100.2376
    },
    {
      "time": "2026-06-15T10:00:00Z",
      "actualIndex": 100.5619,
      "predictedIndex": 100.7858
    },
    {
      "time": "2026-06-15T11:00:00Z",
      "actualIndex": 101.4429,
      "predictedIndex": 100.5334
    },
    {
      "time": "2026-06-15T12:00:00Z",
      "actualIndex": 104.4281,
      "predictedIndex": 101.4122
    },
    {
      "time": "2026-06-15T13:00:00Z",
      "actualIndex": 108.8785,
      "predictedIndex": 104.3949
    },
    {
      "time": "2026-06-15T14:00:00Z",
      "actualIndex": 112.957,
      "predictedIndex": 108.8423
    },
    {
      "time": "2026-06-15T15:00:00Z",
      "actualIndex": 113.2636,
      "predictedIndex": 112.92
    },
    {
      "time": "2026-06-15T16:00:00Z",
      "actualIndex": 120.2129,
      "predictedIndex": 113.2252
    },
    {
      "time": "2026-06-15T17:00:00Z",
      "actualIndex": 122.4427,
      "predictedIndex": 120.171
    },
    {
      "time": "2026-06-15T18:00:00Z",
      "actualIndex": 120.7391,
      "predictedIndex": 122.4024
    },
    {
      "time": "2026-06-15T19:00:00Z",
      "actualIndex": 117.1598,
      "predictedIndex": 120.7015
    },
    {
      "time": "2026-06-15T20:00:00Z",
      "actualIndex": 117.4521,
      "predictedIndex": 117.1242
    },
    {
      "time": "2026-06-15T21:00:00Z",
      "actualIndex": 117.3514,
      "predictedIndex": 117.4168
    },
    {
      "time": "2026-06-15T22:00:00Z",
      "actualIndex": 115.3392,
      "predictedIndex": 117.3168
    },
    {
      "time": "2026-06-15T23:00:00Z",
      "actualIndex": 113.5634,
      "predictedIndex": 115.3054
    },
    {
      "time": "2026-06-16T00:00:00Z",
      "actualIndex": 113.2188,
      "predictedIndex": 113.5304
    },
    {
      "time": "2026-06-16T01:00:00Z",
      "actualIndex": 115.6738,
      "predictedIndex": 113.1856
    },
    {
      "time": "2026-06-16T02:00:00Z",
      "actualIndex": 113.2525,
      "predictedIndex": 115.6378
    },
    {
      "time": "2026-06-16T03:00:00Z",
      "actualIndex": 111.2847,
      "predictedIndex": 113.2142
    },
    {
      "time": "2026-06-16T04:00:00Z",
      "actualIndex": 113.2952,
      "predictedIndex": 111.2466
    },
    {
      "time": "2026-06-16T05:00:00Z",
      "actualIndex": 112.1744,
      "predictedIndex": 113.2545
    },
    {
      "time": "2026-06-16T06:00:00Z",
      "actualIndex": 114.9843,
      "predictedIndex": 112.1295
    },
    {
      "time": "2026-06-16T07:00:00Z",
      "actualIndex": 114.3307,
      "predictedIndex": 114.9325
    },
    {
      "time": "2026-06-16T08:00:00Z",
      "actualIndex": 114.4224,
      "predictedIndex": 114.2754
    },
    {
      "time": "2026-06-16T09:00:00Z",
      "actualIndex": 118.0141,
      "predictedIndex": 114.3631
    },
    {
      "time": "2026-06-16T10:00:00Z",
      "actualIndex": 117.4681,
      "predictedIndex": 117.9477
    },
    {
      "time": "2026-06-16T11:00:00Z",
      "actualIndex": 117.787,
      "predictedIndex": 117.3983
    },
    {
      "time": "2026-06-16T12:00:00Z",
      "actualIndex": 117.7969,
      "predictedIndex": 117.7173
    },
    {
      "time": "2026-06-16T13:00:00Z",
      "actualIndex": 120.253,
      "predictedIndex": 117.7278
    },
    {
      "time": "2026-06-16T14:00:00Z",
      "actualIndex": 119.1624,
      "predictedIndex": 120.193
    },
    {
      "time": "2026-06-16T15:00:00Z",
      "actualIndex": 117.0718,
      "predictedIndex": 119.1077
    },
    {
      "time": "2026-06-16T16:00:00Z",
      "actualIndex": 116.218,
      "predictedIndex": 117.0274
    },
    {
      "time": "2026-06-16T17:00:00Z",
      "actualIndex": 114.4113,
      "predictedIndex": 116.18
    },
    {
      "time": "2026-06-16T18:00:00Z",
      "actualIndex": 115.1349,
      "predictedIndex": 114.3764
    },
    {
      "time": "2026-06-16T19:00:00Z",
      "actualIndex": 117.3625,
      "predictedIndex": 115.1054
    },
    {
      "time": "2026-06-16T20:00:00Z",
      "actualIndex": 116.1624,
      "predictedIndex": 117.3335
    },
    {
      "time": "2026-06-16T21:00:00Z",
      "actualIndex": 117.4726,
      "predictedIndex": 116.1348
    },
    {
      "time": "2026-06-16T22:00:00Z",
      "actualIndex": 116.6485,
      "predictedIndex": 117.4435
    },
    {
      "time": "2026-06-16T23:00:00Z",
      "actualIndex": 116.1435,
      "predictedIndex": 116.6207
    },
    {
      "time": "2026-06-17T00:00:00Z",
      "actualIndex": 114.8721,
      "predictedIndex": 116.1177
    },
    {
      "time": "2026-06-17T01:00:00Z",
      "actualIndex": 116.4551,
      "predictedIndex": 114.8517
    },
    {
      "time": "2026-06-17T02:00:00Z",
      "actualIndex": 119.2244,
      "predictedIndex": 116.4368
    },
    {
      "time": "2026-06-17T03:00:00Z",
      "actualIndex": 120.558,
      "predictedIndex": 119.2064
    },
    {
      "time": "2026-06-17T04:00:00Z",
      "actualIndex": 120.0774,
      "predictedIndex": 120.5386
    },
    {
      "time": "2026-06-17T05:00:00Z",
      "actualIndex": 119.35,
      "predictedIndex": 120.0568
    },
    {
      "time": "2026-06-17T06:00:00Z",
      "actualIndex": 118.8325,
      "predictedIndex": 119.3293
    },
    {
      "time": "2026-06-17T07:00:00Z",
      "actualIndex": 118.3632,
      "predictedIndex": 118.8104
    },
    {
      "time": "2026-06-17T08:00:00Z",
      "actualIndex": 117.5674,
      "predictedIndex": 118.3409
    },
    {
      "time": "2026-06-17T09:00:00Z",
      "actualIndex": 116.2336,
      "predictedIndex": 117.5449
    },
    {
      "time": "2026-06-17T10:00:00Z",
      "actualIndex": 117.2229,
      "predictedIndex": 116.21
    },
    {
      "time": "2026-06-17T11:00:00Z",
      "actualIndex": 116.093,
      "predictedIndex": 117.1962
    },
    {
      "time": "2026-06-17T12:00:00Z",
      "actualIndex": 119.0465,
      "predictedIndex": 116.0639
    },
    {
      "time": "2026-06-17T13:00:00Z",
      "actualIndex": 119.7241,
      "predictedIndex": 119.0158
    },
    {
      "time": "2026-06-17T14:00:00Z",
      "actualIndex": 119.1678,
      "predictedIndex": 119.6935
    },
    {
      "time": "2026-06-17T15:00:00Z",
      "actualIndex": 118.8807,
      "predictedIndex": 119.1373
    },
    {
      "time": "2026-06-17T16:00:00Z",
      "actualIndex": 121.9027,
      "predictedIndex": 118.8496
    },
    {
      "time": "2026-06-17T17:00:00Z",
      "actualIndex": 119.6143,
      "predictedIndex": 121.8706
    },
    {
      "time": "2026-06-17T18:00:00Z",
      "actualIndex": 119.8405,
      "predictedIndex": 119.5829
    },
    {
      "time": "2026-06-17T19:00:00Z",
      "actualIndex": 120.3393,
      "predictedIndex": 119.8096
    },
    {
      "time": "2026-06-17T20:00:00Z",
      "actualIndex": 116.7642,
      "predictedIndex": 120.3081
    },
    {
      "time": "2026-06-17T21:00:00Z",
      "actualIndex": 118.9608,
      "predictedIndex": 116.732
    },
    {
      "time": "2026-06-17T22:00:00Z",
      "actualIndex": 118.8144,
      "predictedIndex": 118.9274
    },
    {
      "time": "2026-06-17T23:00:00Z",
      "actualIndex": 121.1282,
      "predictedIndex": 118.7814
    },
    {
      "time": "2026-06-18T00:00:00Z",
      "actualIndex": 119.5247,
      "predictedIndex": 121.095
    },
    {
      "time": "2026-06-18T01:00:00Z",
      "actualIndex": 121.0355,
      "predictedIndex": 119.4916
    },
    {
      "time": "2026-06-18T02:00:00Z",
      "actualIndex": 127.3517,
      "predictedIndex": 121.0017
    },
    {
      "time": "2026-06-18T03:00:00Z",
      "actualIndex": 126.2161,
      "predictedIndex": 127.3169
    },
    {
      "time": "2026-06-18T04:00:00Z",
      "actualIndex": 123.2949,
      "predictedIndex": 126.1842
    },
    {
      "time": "2026-06-18T05:00:00Z",
      "actualIndex": 122.9684,
      "predictedIndex": 123.2596
    },
    {
      "time": "2026-06-18T06:00:00Z",
      "actualIndex": 121.8384,
      "predictedIndex": 122.9277
    },
    {
      "time": "2026-06-18T07:00:00Z",
      "actualIndex": 122.7324,
      "predictedIndex": 121.7963
    },
    {
      "time": "2026-06-18T08:00:00Z",
      "actualIndex": 125.9864,
      "predictedIndex": 122.6839
    },
    {
      "time": "2026-06-18T09:00:00Z",
      "actualIndex": 126.5864,
      "predictedIndex": 125.9299
    },
    {
      "time": "2026-06-18T10:00:00Z",
      "actualIndex": 128.7741,
      "predictedIndex": 126.5254
    },
    {
      "time": "2026-06-18T11:00:00Z",
      "actualIndex": 126.5434,
      "predictedIndex": 128.7068
    },
    {
      "time": "2026-06-18T12:00:00Z",
      "actualIndex": 125.4131,
      "predictedIndex": 126.473
    },
    {
      "time": "2026-06-18T13:00:00Z",
      "actualIndex": 129.1987,
      "predictedIndex": 125.3346
    },
    {
      "time": "2026-06-18T14:00:00Z",
      "actualIndex": 129.6813,
      "predictedIndex": 129.1132
    },
    {
      "time": "2026-06-18T15:00:00Z",
      "actualIndex": 130.9976,
      "predictedIndex": 129.5827
    },
    {
      "time": "2026-06-18T16:00:00Z",
      "actualIndex": 126.2408,
      "predictedIndex": 130.8909
    },
    {
      "time": "2026-06-18T17:00:00Z",
      "actualIndex": 128.6074,
      "predictedIndex": 126.1236
    },
    {
      "time": "2026-06-18T18:00:00Z",
      "actualIndex": 122.3058,
      "predictedIndex": 128.4889
    },
    {
      "time": "2026-06-18T19:00:00Z",
      "actualIndex": 123.7709,
      "predictedIndex": 122.1813
    },
    {
      "time": "2026-06-18T20:00:00Z",
      "actualIndex": 125.2076,
      "predictedIndex": 123.6391
    },
    {
      "time": "2026-06-18T21:00:00Z",
      "actualIndex": 125.3175,
      "predictedIndex": 125.0733
    },
    {
      "time": "2026-06-18T22:00:00Z",
      "actualIndex": 123.2823,
      "predictedIndex": 125.1848
    },
    {
      "time": "2026-06-18T23:00:00Z",
      "actualIndex": 124.3119,
      "predictedIndex": 123.1484
    },
    {
      "time": "2026-06-19T00:00:00Z",
      "actualIndex": 124.595,
      "predictedIndex": 124.1711
    },
    {
      "time": "2026-06-19T01:00:00Z",
      "actualIndex": 122.9182,
      "predictedIndex": 124.4476
    },
    {
      "time": "2026-06-19T02:00:00Z",
      "actualIndex": 123.1768,
      "predictedIndex": 122.7601
    },
    {
      "time": "2026-06-19T03:00:00Z",
      "actualIndex": 123.1479,
      "predictedIndex": 123.0148
    },
    {
      "time": "2026-06-19T04:00:00Z",
      "actualIndex": 120.1719,
      "predictedIndex": 122.9927
    },
    {
      "time": "2026-06-19T05:00:00Z",
      "actualIndex": 115.9332,
      "predictedIndex": 120.0231
    },
    {
      "time": "2026-06-19T06:00:00Z",
      "actualIndex": 116.7592,
      "predictedIndex": 115.7789
    },
    {
      "time": "2026-06-19T07:00:00Z",
      "actualIndex": 117.5643,
      "predictedIndex": 116.594
    },
    {
      "time": "2026-06-19T08:00:00Z",
      "actualIndex": 115.0085,
      "predictedIndex": 117.3914
    },
    {
      "time": "2026-06-19T09:00:00Z",
      "actualIndex": 116.3716,
      "predictedIndex": 114.8354
    },
    {
      "time": "2026-06-19T10:00:00Z",
      "actualIndex": 116.3756,
      "predictedIndex": 116.2042
    },
    {
      "time": "2026-06-19T11:00:00Z",
      "actualIndex": 115.4856,
      "predictedIndex": 116.2064
    },
    {
      "time": "2026-06-19T12:00:00Z",
      "actualIndex": 114.8394,
      "predictedIndex": 115.3197
    },
    {
      "time": "2026-06-19T13:00:00Z",
      "actualIndex": 114.9058,
      "predictedIndex": 114.6749
    },
    {
      "time": "2026-06-19T14:00:00Z",
      "actualIndex": 117.6413,
      "predictedIndex": 114.7426
    },
    {
      "time": "2026-06-19T15:00:00Z",
      "actualIndex": 117.1175,
      "predictedIndex": 117.475
    },
    {
      "time": "2026-06-19T16:00:00Z",
      "actualIndex": 117.8296,
      "predictedIndex": 116.9475
    },
    {
      "time": "2026-06-19T17:00:00Z",
      "actualIndex": 117.0287,
      "predictedIndex": 117.6584
    },
    {
      "time": "2026-06-19T18:00:00Z",
      "actualIndex": 117.3412,
      "predictedIndex": 116.852
    },
    {
      "time": "2026-06-19T19:00:00Z",
      "actualIndex": 117.2381,
      "predictedIndex": 117.1615
    },
    {
      "time": "2026-06-19T20:00:00Z",
      "actualIndex": 115.9403,
      "predictedIndex": 117.0546
    },
    {
      "time": "2026-06-19T21:00:00Z",
      "actualIndex": 115.7507,
      "predictedIndex": 115.7582
    },
    {
      "time": "2026-06-19T22:00:00Z",
      "actualIndex": null,
      "predictedIndex": 115.5628
    },
    {
      "time": "2026-06-19T23:00:00Z",
      "actualIndex": null,
      "predictedIndex": 115.3691
    },
    {
      "time": "2026-06-20T00:00:00Z",
      "actualIndex": null,
      "predictedIndex": 115.1486
    },
    {
      "time": "2026-06-20T01:00:00Z",
      "actualIndex": null,
      "predictedIndex": 114.9436
    },
    {
      "time": "2026-06-20T02:00:00Z",
      "actualIndex": null,
      "predictedIndex": 114.7237
    },
    {
      "time": "2026-06-20T03:00:00Z",
      "actualIndex": null,
      "predictedIndex": 114.5235
    },
    {
      "time": "2026-06-20T04:00:00Z",
      "actualIndex": null,
      "predictedIndex": 114.318
    },
    {
      "time": "2026-06-20T05:00:00Z",
      "actualIndex": null,
      "predictedIndex": 114.1253
    },
    {
      "time": "2026-06-20T06:00:00Z",
      "actualIndex": null,
      "predictedIndex": 113.9102
    },
    {
      "time": "2026-06-20T07:00:00Z",
      "actualIndex": null,
      "predictedIndex": 113.7374
    },
    {
      "time": "2026-06-20T08:00:00Z",
      "actualIndex": null,
      "predictedIndex": 113.5326
    },
    {
      "time": "2026-06-20T09:00:00Z",
      "actualIndex": null,
      "predictedIndex": 113.3228
    },
    {
      "time": "2026-06-20T10:00:00Z",
      "actualIndex": null,
      "predictedIndex": 113.1014
    },
    {
      "time": "2026-06-20T11:00:00Z",
      "actualIndex": null,
      "predictedIndex": 112.8962
    },
    {
      "time": "2026-06-20T12:00:00Z",
      "actualIndex": null,
      "predictedIndex": 112.6791
    },
    {
      "time": "2026-06-20T13:00:00Z",
      "actualIndex": null,
      "predictedIndex": 112.4478
    },
    {
      "time": "2026-06-20T14:00:00Z",
      "actualIndex": null,
      "predictedIndex": 112.2643
    },
    {
      "time": "2026-06-20T15:00:00Z",
      "actualIndex": null,
      "predictedIndex": 112.0539
    },
    {
      "time": "2026-06-20T16:00:00Z",
      "actualIndex": null,
      "predictedIndex": 111.8347
    },
    {
      "time": "2026-06-20T17:00:00Z",
      "actualIndex": null,
      "predictedIndex": 111.6288
    },
    {
      "time": "2026-06-20T18:00:00Z",
      "actualIndex": null,
      "predictedIndex": 111.4263
    },
    {
      "time": "2026-06-20T19:00:00Z",
      "actualIndex": null,
      "predictedIndex": 111.2257
    },
    {
      "time": "2026-06-20T20:00:00Z",
      "actualIndex": null,
      "predictedIndex": 111.0324
    },
    {
      "time": "2026-06-20T21:00:00Z",
      "actualIndex": null,
      "predictedIndex": 110.8517
    }
  ],
  "signal": {
    "direction": "down",
    "changePercent24h": -2.0796169486894263,
    "confidence": 0.7842
  },
  "commentary": {
    "en": "Stellar (STELLAR) is expected to continue its downtrend with a predicted 24h return of -4.2% due to the bearish sentiment in the market. The recent news on regulatory developments and market trends may not have a significant impact on Stellar's price movement. The Fear & Greed Index at 14 indicates extreme fear, which may contribute to the predicted downtrend.",
    "ja": "ステラ (STELLAR) は、市場の悲観的な感情に加えて、24 時間以内に -4.2% の下落が予想される。規制開発や市場動向に関する最近のニュースは、ステラの価格動向に大きな影響を与える可能性は低い。恐怖と欲求不満指数が 14 であることは、予想される下落に寄与する可能性がある。",
    "sources": [
      {
        "label": "Fear & Greed Index",
        "value": "14 — Extreme Fear",
        "url": "https://alternative.me/crypto/fear-and-greed-index/"
      },
      {
        "label": "RSI-14",
        "value": "40.4 (neutral)",
        "url": "https://www.coingecko.com/en/coins/stellar"
      },
      {
        "label": "Bollinger Band %B",
        "value": "0.33 (mid range)",
        "url": null
      },
      {
        "label": "Volume (24 h ratio)",
        "value": "0.6× average",
        "url": null
      },
      {
        "label": "BTC 24 h return",
        "value": "+0.00%",
        "url": "https://www.coingecko.com/en/coins/bitcoin"
      },
      {
        "label": "Crypto market cap (24 h)",
        "value": "-0.13%",
        "url": "https://www.coingecko.com/en/global-charts"
      },
      {
        "label": "CoinGecko Community Sentiment",
        "value": "57% bullish",
        "url": "https://www.coingecko.com/en/coins/stellar"
      },
      {
        "label": "CoinTelegraph",
        "value": "WhiteBIT secures MiCA license in Austria ahead of July 1 EU deadline",
        "url": "https://cointelegraph.com/news/whitebit-secures-mica-license-austria-gains-access-eu-crypto-market?utm_source=rss&utm_medium=rss&utm_campaign=rss"
      },
      {
        "label": "CoinTelegraph",
        "value": "Republican lawmaker proposes prediction markets insider trading ban, not including White House officials",
        "url": "https://cointelegraph.com/news/prediction-markets-law-white-house-officials?utm_source=rss&utm_medium=rss&utm_campaign=rss"
      },
      {
        "label": "CoinTelegraph",
        "value": "Bitcoin traders expect new lows but data cautions against overly bearish bias",
        "url": "https://cointelegraph.com/markets/bitcoin-eyes-new-yearly-lows-as-traders-warn-not-to-get-too-bearish-here?utm_source=rss&utm_medium=rss&utm_campaign=rss"
      }
    ]
  }
}